{"width": 9, "height": 9, "nodes": [{"id": 14, "x": 1, "y": 4, "cost": 1.3, "name": "church"}, {"id": 56, "x": 5, "y": 6, "cost": 2.3, "name": "theater"}, {"id": 67, "x": 6, "y": 7, "cost": 0.3, "name": "fontain"}, {"id": 36, "x": 3, "y": 6, "cost": 0.5, "name": "university"}, {"id": 60, "x": 6, "y": 0, "cost": 1.1, "name": "diamond"}, {"id": 40, "x": 4, "y": 0, "cost": 0.5, "name": "food"}, {"id": 42, "x": 4, "y": 2, "cost": 1.5, "name": "house"}, {"id": 47, "x": 4, "y": 7, "cost": 1.0, "name": "infocenter"}, {"id": 80, "x": 8, "y": 0, "cost": 0.6, "name": "burgers"}, {"id": 83, "x": 8, "y": 3, "cost": 1.0, "name": "rail"}], "edges": [{"from_id": 14, "to_id": 56, "weight": 4.1}, {"from_id": 14, "to_id": 60, "weight": 2.15}, {"from_id": 14, "to_id": 47, "weight": 3.85}, {"from_id": 14, "to_id": 80, "weight": 3.35}, {"from_id": 14, "to_id": 83, "weight": 3.5}, {"from_id": 56, "to_id": 14, "weight": 0.85}, {"from_id": 56, "to_id": 36, "weight": 2.6}, {"from_id": 56, "to_id": 40, "weight": 1.55}, {"from_id": 56, "to_id": 47, "weight": 4.65}, {"from_id": 67, "to_id": 60, "weight": 2.45}, {"from_id": 67, "to_id": 83, "weight": 4.3}, {"from_id": 36, "to_id": 14, "weight": 4.05}, {"from_id": 36, "to_id": 40, "weight": 0.9}, {"from_id": 36, "to_id": 47, "weight": 4.65}, {"from_id": 60, "to_id": 56, "weight": 4.05}, {"from_id": 60, "to_id": 47, "weight": 4.75}, {"from_id": 60, "to_id": 80, "weight": 3.25}, {"from_id": 60, "to_id": 83, "weight": 3.25}, {"from_id": 40, "to_id": 14, "weight": 1.45}, {"from_id": 40, "to_id": 56, "weight": 2.85}, {"from_id": 40, "to_id": 67, "weight": 3.3}, {"from_id": 40, "to_id": 36, "weight": 0.5}, {"from_id": 40, "to_id": 42, "weight": 4.55}, {"from_id": 40, "to_id": 47, "weight": 4.0}, {"from_id": 40, "to_id": 80, "weight": 4.0}, {"from_id": 42, "to_id": 36, "weight": 2.95}, {"from_id": 42, "to_id": 60, "weight": 1.5}, {"from_id": 42, "to_id": 83, "weight": 3.35}, {"from_id": 47, "to_id": 14, "weight": 4.0}, {"from_id": 47, "to_id": 67, "weight": 4.35}, {"from_id": 47, "to_id": 36, "weight": 1.85}, {"from_id": 47, "to_id": 60, "weight": 1.15}, {"from_id": 47, "to_id": 40, "weight": 4.3}, {"from_id": 47, "to_id": 80, "weight": 2.35}, {"from_id": 80, "to_id": 67, "weight": 4.55}, {"from_id": 80, "to_id": 36, "weight": 1.3}, {"from_id": 80, "to_id": 40, "weight": 4.55}, {"from_id": 80, "to_id": 83, "weight": 3.85}, {"from_id": 83, "to_id": 36, "weight": 0.85}, {"from_id": 83, "to_id": 60, "weight": 4.2}, {"from_id": 83, "to_id": 42, "weight": 2.25}, {"from_id": 83, "to_id": 47, "weight": 1.75}, {"from_id": 83, "to_id": 80, "weight": 2.45}]}